djadmin_formset/__init__.py
djadmin_formset/apps.py
djadmin_formset/default_app_config.py
djadmin_formset/djadmin_hooks.py
djadmin_formset/factories.py
djadmin_formset/mixins.py
djadmin_formset/renderers.py
djadmin_formset/utils.py
djadmin_formset/templates/djadmin/actions/add.html
djadmin_formset/templates/djadmin/actions/edit.html
djadmin_formset-0.1.3.dist-info/licenses/LICENSE
djadmin_formset-0.1.3.dist-info/METADATA
djadmin_formset-0.1.3.dist-info/WHEEL
djadmin_formset-0.1.3.dist-info/entry_points.txt
djadmin_formset-0.1.3.dist-info/top_level.txt
djadmin_formset-0.1.3.dist-info/RECORD
